CryptoTokenAuth/__init__.py
CryptoTokenAuth/authentication.py
CryptoTokenAuth/encryption.py
CryptoTokenAuth/version.py
test/__init__.py
test/test.py
test/tools.py
CryptoTokenAuth-1.0.2.dist-info/METADATA
CryptoTokenAuth-1.0.2.dist-info/WHEEL
CryptoTokenAuth-1.0.2.dist-info/top_level.txt
CryptoTokenAuth-1.0.2.dist-info/RECORD
